mslm/__init__.py
mslm/mslm.py
mslm_email_verify/__init__.py
mslm_email_verify/email_verify.py
mslm_email_verify/single_verify_resp.py
mslm_email_verify/single_verify_resp_mx.py
mslm_lib/__init__.py
mslm_lib/lib.py
mslm_lib/mslm_errors.py
mslm_lib/req_opts.py
mslm_otp/__init__.py
mslm_otp/otp.py
mslm_otp/otp_resp.py
mslm_otp/otp_send_req.py
mslm_otp/otp_token_verify_req.py
mslm_test2-1.0.0.dist-info/LICENSE
mslm_test2-1.0.0.dist-info/METADATA
mslm_test2-1.0.0.dist-info/WHEEL
mslm_test2-1.0.0.dist-info/top_level.txt
mslm_test2-1.0.0.dist-info/RECORD
